<?xml version="1.0" encoding="utf-8"?>

<PropertyList>

  <path>cockpit.ac</path>

  <!--animation>
    <type>material</type>
    <object-name>body_int</object-name>
    <object-name>window_int</object-name>
    <object-name>door_front_right_int</object-name>
    <object-name>door_front_left_int</object-name>
    <object-name>door_back_int</object-name>
    <object-name>floor</object-name>
    <texture-prop>texture</texture-prop>
    <texture>textures/interior.png</texture>
  </animation>

  <model>
    <path>Aircraft/panthera/instruments/all/instruments-model.xml</path>
  </model-->

<!-- USED FOR DEVELOPMENT -->
  <!--animation>
    <type>translate</type>
    <object-name>turn-pilot</object-name>
    <property>/_debug/float1</property>
    <factor>1</factor>
    <axis>
      <x>1</x>
      <y>0</y>
      <z>0</z>
    </axis>
  </animation>
  <animation>
    <type>translate</type>
    <object-name>turn-pilot</object-name>
    <property>/_debug/float2</property>
    <factor>1</factor>
    <axis>
      <x>0</x>
      <y>1</y>
      <z>0</z>
    </axis>
  </animation>
  <animation>
    <type>translate</type>
    <object-name>turn-pilot</object-name>
    <property>/_debug/float3</property>
    <factor>1</factor>
    <axis>
      <x>0</x>
      <y>0</y>
      <z>1</z>
    </axis>
  </animation-->

</PropertyList>
